concurio/__init__.py
concurio/pool.py
concurio/task.py
concurio-0.0.1.dist-info/METADATA
concurio-0.0.1.dist-info/WHEEL
concurio-0.0.1.dist-info/entry_points.txt
concurio-0.0.1.dist-info/license_files/LICENSE
concurio-0.0.1.dist-info/RECORD
