Metadata-Version: 2.1
Name: concurio
Version: 0.0.1
Summary: Simple concurrency pool executors for Python
Project-URL: Homepage, https://github.com/zPy52/concurio
Project-URL: Issues, https://github.com/zPy52/concurio/issues
Project-URL: Repository, https://github.com/zPy52/concurio
Author-email: Antonio Peña Peña <toni@antokel.com>
License:                                  Apache License
Classifier: Development Status :: 3 - Alpha
Classifier: Intended Audience :: Developers
Classifier: License :: OSI Approved :: Apache Software License
Classifier: Programming Language :: Python :: 3
Classifier: Programming Language :: Python :: 3.10
Classifier: Programming Language :: Python :: 3.11
Classifier: Programming Language :: Python :: 3.12
Classifier: Programming Language :: Python :: 3.8
Classifier: Programming Language :: Python :: 3.9
Requires-Python: >=3.8
Requires-Dist: tqdm>=4.40.0
